microcosm/source/game.py
microcosm/source/display/board.py
microcosm/source/display/display_utils.py
microcosm/source/display/menu.py
microcosm/source/display/menu_display.py
microcosm/source/display/overlay.py
microcosm/source/display/overlay_display.py
microcosm/source/foundation/achievements.py
microcosm/source/foundation/catalogue.py
microcosm/source/foundation/models.py
microcosm/source/game_management/game_controller.py
microcosm/source/game_management/game_input_handler.py
microcosm/source/game_management/game_state.py
microcosm/source/game_management/movemaker.py
microcosm/source/networking/client.py
microcosm/source/networking/event_listener.py
microcosm/source/networking/events.py
microcosm/source/resources/achievements.pyxres
microcosm/source/resources/background1.pyxres
microcosm/source/resources/background2.pyxres
microcosm/source/resources/icon.png
microcosm/source/resources/quads.pyxres
microcosm/source/resources/sprites.pyxres
microcosm/source/resources/audio/background1.ogg
microcosm/source/resources/audio/background2.ogg
microcosm/source/resources/audio/background3.ogg
microcosm/source/resources/audio/background4.ogg
microcosm/source/resources/audio/background5.ogg
microcosm/source/resources/audio/background6.ogg
microcosm/source/resources/audio/background7.ogg
microcosm/source/resources/audio/background8.ogg
microcosm/source/resources/audio/menu.ogg
microcosm/source/resources/dll/miniupnpc.dll
microcosm/source/saving/game_save_manager.py
microcosm/source/saving/save_encoder.py
microcosm/source/saving/save_migrator.py
microcosm/source/util/calculator.py
microcosm/source/util/converter.py
microcosm/source/util/minifier.py
microcosm/source/util/music_player.py
microcosm_4x-4.1.1.dist-info/METADATA
microcosm_4x-4.1.1.dist-info/WHEEL
microcosm_4x-4.1.1.dist-info/entry_points.txt
microcosm_4x-4.1.1.dist-info/licenses/COPYING
microcosm_4x-4.1.1.dist-info/RECORD
