Metadata-Version: 2.4
Name: microcosm-4x
Version: 4.1.1
Summary: A little 4X game written using Pyxel.
Project-URL: Documentation, https://github.com/ChrisNeedham24/microcosm#readme
Project-URL: Issues, https://github.com/ChrisNeedham24/microcosm/issues
Project-URL: Source, https://github.com/ChrisNeedham24/microcosm
Author-email: ChrisNeedham24 <christopherneedham24@gmail.com>
License-Expression: GPL-3.0-only
License-File: COPYING
Keywords: 4x,game,pyxel
Classifier: Development Status :: 5 - Production/Stable
Classifier: Programming Language :: Python
Classifier: Programming Language :: Python :: 3.10
Classifier: Programming Language :: Python :: 3.11
Classifier: Programming Language :: Python :: 3.12
Requires-Python: >=3.10
Requires-Dist: miniupnpc==2.0.2; platform_system != 'Windows'
Requires-Dist: miniupnpc==2.2.7; platform_system == 'Windows'
Requires-Dist: pillow==10.3.0
Requires-Dist: platformdirs==3.9.1
Requires-Dist: python-vlc==3.0.16120
Requires-Dist: pyxel==1.9.0
